acopy/__init__.py
acopy/ant.py
acopy/cli.py
acopy/plugins.py
acopy/solvers.py
acopy/utils/__init__.py
acopy/utils/data.py
acopy/utils/general.py
acopy/utils/plot.py
tests/__init__.py
tests/test_ant.py
tests/test_solution.py
tests/test_state.py
acopy-0.6.4.dist-info/AUTHORS.rst
acopy-0.6.4.dist-info/LICENSE
acopy-0.6.4.dist-info/METADATA
acopy-0.6.4.dist-info/WHEEL
acopy-0.6.4.dist-info/entry_points.txt
acopy-0.6.4.dist-info/top_level.txt
acopy-0.6.4.dist-info/zip-safe
acopy-0.6.4.dist-info/RECORD
