Metadata-Version: 2.1
Name: acopy
Version: 0.6.4
Summary: Ant Colony Optimization for Tthe Traveling Salesman Problem.
Home-page: https://github.com/rhgrant10/acopy
Author: Robert Grant
Author-email: rhgrant10@gmail.com
License: Apache Software License 2.0
Keywords: acopy
Platform: UNKNOWN
Classifier: Development Status :: 2 - Pre-Alpha
Classifier: Intended Audience :: Developers
Classifier: License :: OSI Approved :: Apache Software License
Classifier: Natural Language :: English
Classifier: Programming Language :: Python :: 3
Classifier: Programming Language :: Python :: 3.6
Classifier: Programming Language :: Python :: 3.7
Requires-Dist: click (==6.7)
Requires-Dist: networkx (==2.1)
Requires-Dist: tsplib95 (==0.3.2)
Provides-Extra: plot
Requires-Dist: matplotlib (==2.1.1) ; extra == 'plot'
Requires-Dist: pandas (==0.23.3) ; extra == 'plot'
